zuko/__init__.py
zuko/bayesian.py
zuko/conftest.py
zuko/distributions.py
zuko/lazy.py
zuko/mixtures.py
zuko/nn.py
zuko/transforms.py
zuko/utils.py
zuko/flows/__init__.py
zuko/flows/autoregressive.py
zuko/flows/continuous.py
zuko/flows/core.py
zuko/flows/coupling.py
zuko/flows/gaussianization.py
zuko/flows/mixture.py
zuko/flows/neural.py
zuko/flows/polynomial.py
zuko/flows/spline.py
zuko-1.5.0.dist-info/licenses/LICENSE
zuko-1.5.0.dist-info/METADATA
zuko-1.5.0.dist-info/WHEEL
zuko-1.5.0.dist-info/top_level.txt
zuko-1.5.0.dist-info/RECORD
