Metadata-Version: 2.4
Name: zuko
Version: 1.5.0
Summary: Normalizing flows in PyTorch
Author-email: The Probabilists <theprobabilists@gmail.com>
Project-URL: documentation, https://zuko.readthedocs.io
Project-URL: source, https://github.com/probabilists/zuko
Project-URL: tracker, https://github.com/probabilists/zuko/issues
Keywords: torch,normalizing flows,probability,distribution,generative,deep learning
Classifier: Intended Audience :: Developers
Classifier: Intended Audience :: Science/Research
Classifier: License :: OSI Approved :: MIT License
Classifier: Natural Language :: English
Classifier: Operating System :: OS Independent
Classifier: Programming Language :: Python :: 3
Requires-Python: >=3.9
License-File: LICENSE
Requires-Dist: numpy>=1.20.0
Requires-Dist: torch>=1.12.0
Provides-Extra: docs
Requires-Dist: docutils==0.19; extra == "docs"
Requires-Dist: furo==2024.5.6; extra == "docs"
Requires-Dist: myst-nb==1.0.0; extra == "docs"
Requires-Dist: sphinx==7.3.7; extra == "docs"
Provides-Extra: lint
Requires-Dist: pre-commit>=3.7.0; extra == "lint"
Requires-Dist: ruff==0.9.9; extra == "lint"
Provides-Extra: test
Requires-Dist: pytest>=8.0.0; extra == "test"
Dynamic: license-file
